qeGraphMaker/__init__.py
qeGraphMaker/apiRequest.py
qeGraphMaker/createFile.py
qeGraphMaker/getGraph.py
qeGraphMaker/graph.py
qeGraphMaker/graphFileParser.py
qeGraphMaker/helper.py
qeGraphMaker/xeqt.py
qeGraphMaker-1.0.5.dist-info/METADATA
qeGraphMaker-1.0.5.dist-info/RECORD
qeGraphMaker-1.0.5.dist-info/WHEEL
qeGraphMaker-1.0.5.dist-info/entry_points.txt
qeGraphMaker-1.0.5.dist-info/top_level.txt
